{"cliente": "UniBrasil · Mestrado & Doutorado", "moeda": "R$", "gerado_em": "23/07/2026", "dmin": "2026-06-25", "dmax": "2026-07-22", "meta": [{"d": "2026-06-25", "c": "BRAND-ACAO-CADASTRO-PRESENCIAL-MESTRADO_DOUTORADO", "ad": "AD01", "m": "PRESENCIAL", "cu": "", "br": true, "sp": 162.94, "ld": 0, "im": 8662, "ck": 88, "tp": 0}, {"d": "2026-06-26", "c": "BRAND-ACAO-CADASTRO-PRESENCIAL-MESTRADO_DOUTORADO", "ad": "AD01", "m": "PRESENCIAL", "cu": "", "br": true, "sp": 120.61, "ld": 2, "im": 6609, "ck": 52, "tp": 0}, {"d": "2026-06-27", "c": "BRAND-ACAO-CADASTRO-PRESENCIAL-MESTRADO_DOUTORADO", "ad": "AD01", "m": "PRESENCIAL", "cu": "", "br": true, "sp": 266.38, "ld": 0, "im": 13771, "ck": 132, "tp": 0}, {"d": "2026-06-28", "c": "BRAND-ACAO-CADASTRO-PRESENCIAL-MESTRADO_DOUTORADO", "ad": "AD01", "m": "PRESENCIAL", "cu": "", "br": true, "sp": 85.21, "ld": 0, "im": 6240, "ck": 98, "tp": 0}, {"d": "2026-06-29", "c": "BRAND-ACAO-CADASTRO-PRESENCIAL-MESTRADO_DOUTORADO", "ad": "AD01", "m": "PRESENCIAL", "cu": "", "br": true, "sp": 162.89, "ld": 0, "im": 18457, "ck": 161, "tp": 0}, {"d": "2026-06-30", "c": "BRAND-ACAO-CADASTRO-PRESENCIAL-MESTRADO_DOUTORADO", "ad": "AD01", "m": "PRESENCIAL", "cu": "", "br": true, "sp": 152.64, "ld": 3, "im": 17052, "ck": 150, "tp": 0}, {"d": "2026-07-01", "c": "BRAND-ACAO-CADASTRO-PRESENCIAL-MESTRADO_DOUTORADO", "ad": "AD01", "m": "PRESENCIAL", "cu": "", "br": true, "sp": 20.49, "ld": 0, "im": 1579, "ck": 3, "tp": 0}, {"d": "2026-07-01", "c": "BRAND-ACAO-CADASTRO-PRESENCIAL-MESTRADO_DOUTORADO", "ad": "AD01", "m": "PRESENCIAL", "cu": "", "br": true, "sp": 40.88, "ld": 0, "im": 3303, "ck": 24, "tp": 0}, {"d": "2026-07-01", "c": "BRAND-ACAO-CADASTRO-PRESENCIAL-MESTRADO_DOUTORADO", "ad": "AD02", "m": "PRESENCIAL", "cu": "", "br": true, "sp": 15.89, "ld": 0, "im": 1070, "ck": 17, "tp": 44}, {"d": "2026-07-01", "c": "BRAND-ACAO-CADASTRO-PRESENCIAL-MESTRADO_DOUTORADO", "ad": "AD02", "m": "PRESENCIAL", "cu": "", "br": true, "sp": 12.6, "ld": 0, "im": 983, "ck": 7, "tp": 18}, {"d": "2026-07-02", "c": "BRAND-ACAO-CADASTRO-PRESENCIAL-MESTRADO_DOUTORADO", "ad": "AD01", "m": "PRESENCIAL", "cu": "", "br": true, "sp": 79.92, "ld": 0, "im": 5086, "ck": 21, "tp": 0}, {"d": "2026-07-02", "c": "BRAND-ACAO-CADASTRO-PRESENCIAL-MESTRADO_DOUTORADO", "ad": "AD02", "m": "PRESENCIAL", "cu": "", "br": true, "sp": 25.08, "ld": 0, "im": 1916, "ck": 21, "tp": 61}, {"d": "2026-07-03", "c": "BRAND-ACAO-CADASTRO-PRESENCIAL-MESTRADO_DOUTORADO", "ad": "AD01", "m": "PRESENCIAL", "cu": "", "br": true, "sp": 13.01, "ld": 0, "im": 468, "ck": 1, "tp": 0}, {"d": "2026-07-03", "c": "BRAND-ACAO-CADASTRO-PRESENCIAL-MESTRADO_DOUTORADO", "ad": "AD02", "m": "PRESENCIAL", "cu": "", "br": true, "sp": 5.88, "ld": 5, "im": 273, "ck": 13, "tp": 22}, {"d": "2026-07-04", "c": "BRAND-ACAO-CADASTRO-PRESENCIAL-MESTRADO_DOUTORADO", "ad": "AD01", "m": "PRESENCIAL", "cu": "", "br": true, "sp": 13.18, "ld": 0, "im": 573, "ck": 4, "tp": 0}, {"d": "2026-07-04", "c": "BRAND-ACAO-CADASTRO-PRESENCIAL-MESTRADO_DOUTORADO", "ad": "AD02", "m": "PRESENCIAL", "cu": "", "br": true, "sp": 1.8, "ld": 0, "im": 74, "ck": 5, "tp": 5}, {"d": "2026-07-05", "c": "BRAND-ACAO-CADASTRO-PRESENCIAL-MESTRADO_DOUTORADO", "ad": "AD01", "m": "PRESENCIAL", "cu": "", "br": true, "sp": 13.85, "ld": 0, "im": 518, "ck": 5, "tp": 0}, {"d": "2026-07-05", "c": "BRAND-ACAO-CADASTRO-PRESENCIAL-MESTRADO_DOUTORADO", "ad": "AD02", "m": "PRESENCIAL", "cu": "", "br": true, "sp": 40.68, "ld": 2, "im": 2168, "ck": 47, "tp": 112}, {"d": "2026-07-06", "c": "BRAND-ACAO-CADASTRO-PRESENCIAL-MESTRADO_DOUTORADO", "ad": "AD01", "m": "PRESENCIAL", "cu": "", "br": true, "sp": 3.6, "ld": 0, "im": 158, "ck": 0, "tp": 0}, {"d": "2026-07-06", "c": "BRAND-ACAO-CADASTRO-PRESENCIAL-MESTRADO_DOUTORADO", "ad": "AD02", "m": "PRESENCIAL", "cu": "", "br": true, "sp": 93.86, "ld": 9, "im": 4852, "ck": 99, "tp": 252}, {"d": "2026-07-07", "c": "BRAND-ACAO-CADASTRO-PRESENCIAL-MESTRADO_DOUTORADO", "ad": "AD01", "m": "PRESENCIAL", "cu": "", "br": true, "sp": 1.9, "ld": 0, "im": 77, "ck": 0, "tp": 0}, {"d": "2026-07-07", "c": "BRAND-ACAO-CADASTRO-PRESENCIAL-MESTRADO_DOUTORADO", "ad": "AD02", "m": "PRESENCIAL", "cu": "", "br": true, "sp": 90.75, "ld": 20, "im": 4914, "ck": 104, "tp": 302}, {"d": "2026-07-08", "c": "BRAND-ACAO-CADASTRO-PRESENCIAL-MESTRADO_DOUTORADO", "ad": "AD02", "m": "PRESENCIAL", "cu": "", "br": true, "sp": 71.84, "ld": 3, "im": 4040, "ck": 74, "tp": 285}, {"d": "2026-07-09", "c": "BRAND-ACAO-CADASTRO-PRESENCIAL-MESTRADO_DOUTORADO", "ad": "AD01", "m": "PRESENCIAL", "cu": "", "br": true, "sp": 0.15, "ld": 0, "im": 8, "ck": 0, "tp": 0}, {"d": "2026-07-09", "c": "BRAND-ACAO-CADASTRO-PRESENCIAL-MESTRADO_DOUTORADO", "ad": "AD02", "m": "PRESENCIAL", "cu": "", "br": true, "sp": 48.33, "ld": 4, "im": 3078, "ck": 72, "tp": 176}, {"d": "2026-07-10", "c": "BRAND-ACAO-CADASTRO-PRESENCIAL-MESTRADO_DOUTORADO", "ad": "AD01", "m": "PRESENCIAL", "cu": "", "br": true, "sp": 0.03, "ld": 0, "im": 5, "ck": 0, "tp": 0}, {"d": "2026-07-10", "c": "BRAND-ACAO-CADASTRO-PRESENCIAL-MESTRADO_DOUTORADO", "ad": "AD02", "m": "PRESENCIAL", "cu": "", "br": true, "sp": 131.34, "ld": 1, "im": 7616, "ck": 120, "tp": 337}, {"d": "2026-07-11", "c": "BRAND-ACAO-CADASTRO-PRESENCIAL-MESTRADO_DOUTORADO", "ad": "AD01", "m": "PRESENCIAL", "cu": "", "br": true, "sp": 0.21, "ld": 0, "im": 17, "ck": 0, "tp": 0}, {"d": "2026-07-11", "c": "BRAND-ACAO-CADASTRO-PRESENCIAL-MESTRADO_DOUTORADO", "ad": "AD02", "m": "PRESENCIAL", "cu": "", "br": true, "sp": 162.01, "ld": 6, "im": 8164, "ck": 144, "tp": 415}, {"d": "2026-07-12", "c": "BRAND-ACAO-CADASTRO-PRESENCIAL-MESTRADO_DOUTORADO", "ad": "AD01", "m": "PRESENCIAL", "cu": "", "br": true, "sp": 3.6, "ld": 0, "im": 187, "ck": 2, "tp": 0}, {"d": "2026-07-12", "c": "BRAND-ACAO-CADASTRO-PRESENCIAL-MESTRADO_DOUTORADO", "ad": "AD02", "m": "PRESENCIAL", "cu": "", "br": true, "sp": 133.22, "ld": 4, "im": 6778, "ck": 101, "tp": 305}, {"d": "2026-07-13", "c": "BRAND-ACAO-CADASTRO-PRESENCIAL-MESTRADO_DOUTORADO", "ad": "AD01", "m": "PRESENCIAL", "cu": "", "br": true, "sp": 14.95, "ld": 2, "im": 1026, "ck": 14, "tp": 0}, {"d": "2026-07-13", "c": "BRAND-ACAO-CADASTRO-PRESENCIAL-MESTRADO_DOUTORADO", "ad": "AD02", "m": "PRESENCIAL", "cu": "", "br": true, "sp": 124.6, "ld": 4, "im": 5633, "ck": 96, "tp": 291}, {"d": "2026-07-14", "c": "BRAND-ACAO-CADASTRO-PRESENCIAL-MESTRADO_DOUTORADO", "ad": "AD01", "m": "PRESENCIAL", "cu": "", "br": true, "sp": 39.27, "ld": 5, "im": 2999, "ck": 31, "tp": 0}, {"d": "2026-07-14", "c": "BRAND-ACAO-CADASTRO-PRESENCIAL-MESTRADO_DOUTORADO", "ad": "AD02", "m": "PRESENCIAL", "cu": "", "br": true, "sp": 119.1, "ld": 2, "im": 5110, "ck": 60, "tp": 265}, {"d": "2026-07-15", "c": "BRAND-ACAO-CADASTRO-PRESENCIAL-MESTRADO_DOUTORADO", "ad": "AD01", "m": "PRESENCIAL", "cu": "", "br": true, "sp": 73.89, "ld": 3, "im": 5113, "ck": 32, "tp": 0}, {"d": "2026-07-15", "c": "BRAND-ACAO-CADASTRO-PRESENCIAL-MESTRADO_DOUTORADO", "ad": "AD02", "m": "PRESENCIAL", "cu": "", "br": true, "sp": 85.62, "ld": 1, "im": 3958, "ck": 55, "tp": 206}, {"d": "2026-07-16", "c": "BRAND-ACAO-CADASTRO-PRESENCIAL-MESTRADO_DOUTORADO", "ad": "AD01", "m": "PRESENCIAL", "cu": "", "br": true, "sp": 122.16, "ld": 3, "im": 6402, "ck": 37, "tp": 0}, {"d": "2026-07-16", "c": "BRAND-ACAO-CADASTRO-PRESENCIAL-MESTRADO_DOUTORADO", "ad": "AD02", "m": "PRESENCIAL", "cu": "", "br": true, "sp": 190.81, "ld": 3, "im": 8103, "ck": 122, "tp": 430}, {"d": "2026-07-16", "c": "BRAND-ACAO-CADASTRO-PRESENCIAL-MESTRADO_DOUTORADO", "ad": "AD03", "m": "PRESENCIAL", "cu": "", "br": true, "sp": 167.03, "ld": 2, "im": 7752, "ck": 64, "tp": 213}, {"d": "2026-07-17", "c": "BRAND-ACAO-CADASTRO-PRESENCIAL-MESTRADO_DOUTORADO", "ad": "AD01", "m": "PRESENCIAL", "cu": "", "br": true, "sp": 298.88, "ld": 7, "im": 13745, "ck": 93, "tp": 0}, {"d": "2026-07-17", "c": "BRAND-ACAO-CADASTRO-PRESENCIAL-MESTRADO_DOUTORADO", "ad": "AD02", "m": "PRESENCIAL", "cu": "", "br": true, "sp": 312.74, "ld": 2, "im": 11358, "ck": 136, "tp": 576}, {"d": "2026-07-17", "c": "BRAND-ACAO-CADASTRO-PRESENCIAL-MESTRADO_DOUTORADO", "ad": "AD03", "m": "PRESENCIAL", "cu": "", "br": true, "sp": 146.7, "ld": 4, "im": 5628, "ck": 77, "tp": 236}, {"d": "2026-07-18", "c": "BRAND-ACAO-CADASTRO-PRESENCIAL-MESTRADO_DOUTORADO", "ad": "AD01", "m": "PRESENCIAL", "cu": "", "br": true, "sp": 607.19, "ld": 6, "im": 25321, "ck": 172, "tp": 0}, {"d": "2026-07-18", "c": "BRAND-ACAO-CADASTRO-PRESENCIAL-MESTRADO_DOUTORADO", "ad": "AD02", "m": "PRESENCIAL", "cu": "", "br": true, "sp": 133.89, "ld": 3, "im": 3745, "ck": 61, "tp": 250}, {"d": "2026-07-18", "c": "BRAND-ACAO-CADASTRO-PRESENCIAL-MESTRADO_DOUTORADO", "ad": "AD03", "m": "PRESENCIAL", "cu": "", "br": true, "sp": 98.05, "ld": 1, "im": 3578, "ck": 29, "tp": 119}, {"d": "2026-07-19", "c": "BRAND-ACAO-CADASTRO-PRESENCIAL-MESTRADO_DOUTORADO", "ad": "AD01", "m": "PRESENCIAL", "cu": "", "br": true, "sp": 553.38, "ld": 7, "im": 23979, "ck": 163, "tp": 0}, {"d": "2026-07-19", "c": "BRAND-ACAO-CADASTRO-PRESENCIAL-MESTRADO_DOUTORADO", "ad": "AD02", "m": "PRESENCIAL", "cu": "", "br": true, "sp": 160.98, "ld": 1, "im": 4585, "ck": 89, "tp": 396}, {"d": "2026-07-19", "c": "BRAND-ACAO-CADASTRO-PRESENCIAL-MESTRADO_DOUTORADO", "ad": "AD03", "m": "PRESENCIAL", "cu": "", "br": true, "sp": 75.98, "ld": 0, "im": 3209, "ck": 29, "tp": 138}, {"d": "2026-07-20", "c": "BRAND-ACAO-CADASTRO-PRESENCIAL-MESTRADO_DOUTORADO", "ad": "AD01", "m": "PRESENCIAL", "cu": "", "br": true, "sp": 600.84, "ld": 11, "im": 29418, "ck": 169, "tp": 0}, {"d": "2026-07-20", "c": "BRAND-ACAO-CADASTRO-PRESENCIAL-MESTRADO_DOUTORADO", "ad": "AD02", "m": "PRESENCIAL", "cu": "", "br": true, "sp": 208.73, "ld": 6, "im": 5852, "ck": 78, "tp": 413}, {"d": "2026-07-20", "c": "BRAND-ACAO-CADASTRO-PRESENCIAL-MESTRADO_DOUTORADO", "ad": "AD03", "m": "PRESENCIAL", "cu": "", "br": true, "sp": 48.42, "ld": 1, "im": 2082, "ck": 14, "tp": 106}, {"d": "2026-07-21", "c": "BRAND-ACAO-CADASTRO-PRESENCIAL-MESTRADO_DOUTORADO", "ad": "AD01", "m": "PRESENCIAL", "cu": "", "br": true, "sp": 650.78, "ld": 14, "im": 33130, "ck": 200, "tp": 0}, {"d": "2026-07-21", "c": "BRAND-ACAO-CADASTRO-PRESENCIAL-MESTRADO_DOUTORADO", "ad": "AD02", "m": "PRESENCIAL", "cu": "", "br": true, "sp": 156.36, "ld": 7, "im": 4509, "ck": 83, "tp": 332}, {"d": "2026-07-21", "c": "BRAND-ACAO-CADASTRO-PRESENCIAL-MESTRADO_DOUTORADO", "ad": "AD03", "m": "PRESENCIAL", "cu": "", "br": true, "sp": 48.18, "ld": 3, "im": 1647, "ck": 38, "tp": 124}, {"d": "2026-07-22", "c": "BRAND-ACAO-CADASTRO-PRESENCIAL-MESTRADO_DOUTORADO", "ad": "AD01", "m": "PRESENCIAL", "cu": "", "br": true, "sp": 558.35, "ld": 9, "im": 28336, "ck": 134, "tp": 0}, {"d": "2026-07-22", "c": "BRAND-ACAO-CADASTRO-PRESENCIAL-MESTRADO_DOUTORADO", "ad": "AD02", "m": "PRESENCIAL", "cu": "", "br": true, "sp": 167.61, "ld": 3, "im": 5083, "ck": 76, "tp": 346}, {"d": "2026-07-22", "c": "BRAND-ACAO-CADASTRO-PRESENCIAL-MESTRADO_DOUTORADO", "ad": "AD03", "m": "PRESENCIAL", "cu": "", "br": true, "sp": 35.93, "ld": 4, "im": 1259, "ck": 16, "tp": 75}], "google": [], "demo": [[0, 0, 0, 0, 17.25, 0], [0, 0, 0, 1, 11.18, 0], [0, 0, 0, 2, 0.03, 0], [0, 0, 1, 0, 51.53, 0], [0, 0, 1, 1, 35.4, 0], [0, 0, 1, 2, 0.15, 0], [0, 0, 2, 0, 25.5, 0], [0, 0, 2, 1, 21.84, 0], [0, 0, 2, 2, 0.06, 0], [1, 0, 0, 0, 13.69, 0], [1, 0, 0, 1, 8.49, 0], [1, 0, 0, 2, 0.03, 0], [1, 0, 1, 0, 37.47, 2], [1, 0, 1, 1, 24.43, 0], [1, 0, 1, 2, 0.13, 0], [1, 0, 2, 0, 22.2, 0], [1, 0, 2, 1, 14.1, 0], [1, 0, 2, 2, 0.07, 0], [2, 0, 0, 0, 34.65, 0], [2, 0, 0, 1, 19.07, 0], [2, 0, 0, 2, 0.11, 0], [2, 0, 1, 0, 89.75, 0], [2, 0, 1, 1, 48.95, 0], [2, 0, 1, 2, 0.47, 0], [2, 0, 2, 0, 47.44, 0], [2, 0, 2, 1, 25.82, 0], [2, 0, 2, 2, 0.12, 0], [3, 0, 0, 0, 8.96, 0], [3, 0, 0, 1, 6.92, 0], [3, 0, 0, 2, 0.04, 0], [3, 0, 1, 0, 24.64, 0], [3, 0, 1, 1, 20.96, 0], [3, 0, 1, 2, 0.09, 0], [3, 0, 2, 0, 15.89, 0], [3, 0, 2, 1, 7.66, 0], [3, 0, 2, 2, 0.05, 0], [4, 0, 0, 0, 25.78, 0], [4, 0, 0, 1, 14.8, 0], [4, 0, 0, 2, 0.04, 0], [4, 0, 1, 0, 54.26, 0], [4, 0, 1, 1, 34.35, 0], [4, 0, 1, 2, 0.08, 0], [4, 0, 2, 0, 20.22, 0], [4, 0, 2, 1, 13.23, 0], [4, 0, 2, 2, 0.12, 0], [4, 0, 3, 0, 0.01, 0], [5, 0, 0, 0, 25.68, 1], [5, 0, 0, 1, 16.97, 0], [5, 0, 0, 2, 0.02, 0], [5, 0, 1, 0, 51.44, 1], [5, 0, 1, 1, 30.2, 0], [5, 0, 1, 2, 0.32, 0], [5, 0, 2, 0, 16.0, 1], [5, 0, 2, 1, 11.96, 0], [5, 0, 2, 2, 0.05, 0], [6, 0, 0, 0, 14.93, 0], [6, 0, 0, 1, 8.77, 0], [6, 0, 0, 2, 0.02, 0], [6, 0, 1, 0, 27.35, 0], [6, 0, 1, 1, 18.82, 0], [6, 0, 1, 2, 0.09, 0], [6, 0, 2, 0, 12.53, 0], [6, 0, 2, 1, 7.34, 0], [6, 0, 2, 2, 0.01, 0], [7, 0, 0, 0, 12.8, 0], [7, 0, 0, 1, 10.52, 0], [7, 0, 0, 2, 0.12, 0], [7, 0, 1, 0, 33.5, 0], [7, 0, 1, 1, 22.79, 0], [7, 0, 1, 2, 0.18, 0], [7, 0, 2, 0, 16.2, 0], [7, 0, 2, 1, 8.76, 0], [7, 0, 2, 2, 0.13, 0], [8, 0, 0, 0, 1.56, 0], [8, 0, 0, 1, 1.47, 0], [8, 0, 1, 0, 6.72, 5], [8, 0, 1, 1, 4.72, 0], [8, 0, 2, 0, 2.06, 0], [8, 0, 2, 1, 2.34, 0], [8, 0, 2, 2, 0.02, 0], [9, 0, 0, 0, 1.23, 0], [9, 0, 0, 1, 1.08, 0], [9, 0, 1, 0, 3.82, 0], [9, 0, 1, 1, 3.38, 0], [9, 0, 1, 2, 0.05, 0], [9, 0, 2, 0, 2.65, 0], [9, 0, 2, 1, 2.75, 0], [9, 0, 2, 2, 0.02, 0], [10, 0, 0, 0, 4.22, 0], [10, 0, 0, 1, 3.4, 0], [10, 0, 0, 2, 0.01, 0], [10, 0, 1, 0, 14.9, 0], [10, 0, 1, 1, 12.85, 1], [10, 0, 1, 2, 0.21, 0], [10, 0, 2, 0, 10.6, 1], [10, 0, 2, 1, 8.19, 0], [10, 0, 2, 2, 0.15, 0], [11, 0, 0, 0, 9.64, 0], [11, 0, 0, 1, 9.2, 1], [11, 0, 0, 2, 0.03, 0], [11, 0, 1, 0, 24.6, 5], [11, 0, 1, 1, 22.87, 1], [11, 0, 1, 2, 0.16, 0], [11, 0, 2, 0, 17.18, 1], [11, 0, 2, 1, 13.67, 1], [11, 0, 2, 2, 0.06, 0], [11, 0, 3, 0, 0.01, 0], [11, 0, 3, 1, 0.04, 0], [12, 0, 0, 0, 8.52, 1], [12, 0, 0, 1, 9.74, 1], [12, 0, 0, 2, 0.02, 0], [12, 0, 1, 0, 24.81, 10], [12, 0, 1, 1, 25.9, 6], [12, 0, 1, 2, 0.05, 0], [12, 0, 2, 0, 11.28, 0], [12, 0, 2, 1, 12.32, 2], [12, 0, 3, 1, 0.01, 0], [13, 0, 0, 0, 5.28, 0], [13, 0, 0, 1, 8.42, 0], [13, 0, 0, 2, 0.02, 0], [13, 0, 1, 0, 17.3, 2], [13, 0, 1, 1, 21.26, 0], [13, 0, 2, 0, 8.66, 1], [13, 0, 2, 1, 10.87, 0], [13, 0, 2, 2, 0.02, 0], [13, 0, 3, 0, 0.01, 0], [14, 0, 0, 0, 4.26, 0], [14, 0, 0, 1, 5.2, 0], [14, 0, 0, 2, 0.01, 0], [14, 0, 1, 0, 12.49, 4], [14, 0, 1, 1, 14.72, 0], [14, 0, 1, 2, 0.02, 0], [14, 0, 2, 0, 5.82, 0], [14, 0, 2, 1, 5.95, 0], [14, 0, 2, 2, 0.01, 0], [15, 0, 0, 0, 12.52, 0], [15, 0, 0, 1, 13.6, 0], [15, 0, 0, 2, 0.02, 0], [15, 0, 1, 0, 36.78, 1], [15, 0, 1, 1, 36.3, 0], [15, 0, 1, 2, 0.04, 0], [15, 0, 2, 0, 16.36, 0], [15, 0, 2, 1, 15.71, 0], [15, 0, 2, 2, 0.04, 0], [16, 0, 0, 0, 15.44, 0], [16, 0, 0, 1, 18.14, 2], [16, 0, 0, 2, 0.05, 0], [16, 0, 1, 0, 40.55, 0], [16, 0, 1, 1, 43.14, 1], [16, 0, 1, 2, 0.09, 0], [16, 0, 2, 0, 21.06, 2], [16, 0, 2, 1, 23.71, 1], [16, 0, 2, 2, 0.04, 0], [17, 0, 0, 0, 13.6, 0], [17, 0, 0, 1, 14.37, 0], [17, 0, 0, 2, 0.02, 0], [17, 0, 1, 0, 36.4, 1], [17, 0, 1, 1, 37.16, 3], [17, 0, 1, 2, 0.03, 0], [17, 0, 2, 0, 17.33, 0], [17, 0, 2, 1, 17.82, 0], [17, 0, 2, 2, 0.09, 0], [18, 0, 0, 0, 13.72, 1], [18, 0, 0, 1, 13.82, 0], [18, 0, 0, 2, 0.09, 0], [18, 0, 1, 0, 41.99, 1], [18, 0, 1, 1, 31.91, 2], [18, 0, 1, 2, 0.1, 0], [18, 0, 2, 0, 21.12, 2], [18, 0, 2, 1, 16.44, 0], [18, 0, 2, 2, 0.35, 0], [18, 0, 3, 1, 0.01, 0], [19, 0, 0, 0, 16.24, 1], [19, 0, 0, 1, 15.22, 1], [19, 0, 0, 2, 0.01, 0], [19, 0, 1, 0, 43.17, 3], [19, 0, 1, 1, 35.91, 0], [19, 0, 1, 2, 0.1, 0], [19, 0, 2, 0, 27.04, 0], [19, 0, 2, 1, 20.6, 2], [19, 0, 2, 2, 0.08, 0], [20, 0, 0, 0, 18.02, 1], [20, 0, 0, 1, 15.97, 0], [20, 0, 0, 2, 0.03, 0], [20, 0, 1, 0, 44.31, 2], [20, 0, 1, 1, 37.77, 0], [20, 0, 1, 2, 0.09, 0], [20, 0, 2, 0, 23.58, 0], [20, 0, 2, 1, 19.57, 1], [20, 0, 2, 2, 0.15, 0], [20, 0, 3, 1, 0.02, 0], [21, 0, 0, 0, 51.4, 2], [21, 0, 0, 1, 51.08, 0], [21, 0, 0, 2, 0.16, 0], [21, 0, 1, 0, 125.95, 4], [21, 0, 1, 1, 122.92, 2], [21, 0, 1, 2, 0.28, 0], [21, 0, 2, 0, 70.36, 0], [21, 0, 2, 1, 57.17, 0], [21, 0, 2, 2, 0.68, 0], [22, 0, 0, 0, 86.97, 4], [22, 0, 0, 1, 70.28, 2], [22, 0, 0, 2, 0.24, 0], [22, 0, 1, 0, 225.03, 2], [22, 0, 1, 1, 178.43, 1], [22, 0, 1, 2, 1.58, 0], [22, 0, 2, 0, 109.29, 4], [22, 0, 2, 1, 85.3, 0], [22, 0, 2, 2, 1.2, 0], [23, 0, 0, 0, 83.19, 1], [23, 0, 0, 1, 61.83, 1], [23, 0, 0, 2, 0.05, 0], [23, 0, 1, 0, 258.31, 4], [23, 0, 1, 1, 190.93, 2], [23, 0, 1, 2, 1.52, 0], [23, 0, 2, 0, 144.41, 1], [23, 0, 2, 1, 98.21, 1], [23, 0, 2, 2, 0.65, 0], [23, 0, 3, 0, 0.02, 0], [23, 0, 3, 1, 0.01, 0], [24, 0, 0, 0, 81.64, 1], [24, 0, 0, 1, 55.6, 0], [24, 0, 0, 2, 0.36, 0], [24, 0, 1, 0, 250.94, 5], [24, 0, 1, 1, 163.94, 1], [24, 0, 1, 2, 1.01, 0], [24, 0, 2, 0, 148.31, 0], [24, 0, 2, 1, 87.48, 1], [24, 0, 2, 2, 0.58, 0], [24, 0, 3, 0, 0.15, 0], [24, 0, 3, 1, 0.33, 0], [25, 0, 0, 0, 96.2, 0], [25, 0, 0, 1, 67.44, 3], [25, 0, 0, 2, 0.25, 0], [25, 0, 1, 0, 275.51, 9], [25, 0, 1, 1, 176.66, 2], [25, 0, 1, 2, 0.89, 0], [25, 0, 2, 0, 146.62, 2], [25, 0, 2, 1, 93.7, 2], [25, 0, 2, 2, 0.68, 0], [25, 0, 3, 1, 0.04, 0], [26, 0, 0, 0, 100.76, 3], [26, 0, 0, 1, 69.81, 3], [26, 0, 0, 2, 0.55, 0], [26, 0, 1, 0, 270.76, 11], [26, 0, 1, 1, 173.62, 4], [26, 0, 1, 2, 1.41, 0], [26, 0, 2, 0, 147.44, 3], [26, 0, 2, 1, 90.25, 0], [26, 0, 2, 2, 0.57, 0], [26, 0, 3, 0, 0.04, 0], [26, 0, 3, 1, 0.11, 0], [27, 0, 0, 0, 86.72, 0], [27, 0, 0, 1, 59.42, 0], [27, 0, 0, 2, 0.19, 0], [27, 0, 1, 0, 235.05, 7], [27, 0, 1, 1, 153.54, 3], [27, 0, 1, 2, 0.69, 0], [27, 0, 2, 0, 133.14, 2], [27, 0, 2, 1, 92.71, 4], [27, 0, 2, 2, 0.4, 0], [27, 0, 3, 0, 0.01, 0]], "pos": [[0, 0, 0, 0.04, 0], [0, 0, 2, 0.01, 0], [0, 0, 3, 0.15, 0], [0, 0, 4, 2.06, 0], [0, 0, 5, 0.03, 0], [0, 0, 6, 1.14, 0], [0, 0, 7, 113.66, 0], [0, 0, 8, 0.05, 0], [0, 0, 9, 12.15, 0], [0, 0, 10, 32.03, 0], [0, 0, 12, 0.02, 0], [0, 0, 14, 0.03, 0], [0, 0, 16, 1.56, 0], [1, 0, 0, 0.29, 0], [1, 0, 2, 0.18, 0], [1, 0, 3, 0.01, 0], [1, 0, 4, 0.89, 0], [1, 0, 5, 0.07, 0], [1, 0, 6, 1.01, 0], [1, 0, 7, 77.21, 0], [1, 0, 8, 0.01, 0], [1, 0, 9, 7.89, 0], [1, 0, 10, 32.15, 1], [1, 0, 11, 0.04, 1], [1, 0, 12, 0.09, 0], [1, 0, 14, 0.06, 0], [1, 0, 15, 0.01, 0], [1, 0, 16, 0.7, 0], [2, 0, 0, 3.23, 0], [2, 0, 2, 0.18, 0], [2, 0, 3, 0.04, 0], [2, 0, 4, 3.34, 0], [2, 0, 5, 0.4, 0], [2, 0, 6, 1.97, 0], [2, 0, 7, 162.48, 0], [2, 0, 8, 0.03, 0], [2, 0, 9, 19.94, 0], [2, 0, 10, 72.88, 0], [2, 0, 11, 0.27, 0], [2, 0, 12, 0.1, 0], [2, 0, 14, 0.08, 0], [2, 0, 15, 0.01, 0], [2, 0, 16, 1.43, 0], [3, 0, 0, 8.28, 0], [3, 0, 2, 1.06, 0], [3, 0, 3, 0.03, 0], [3, 0, 4, 1.47, 0], [3, 0, 5, 0.59, 0], [3, 0, 6, 0.89, 0], [3, 0, 7, 49.0, 0], [3, 0, 8, 0.05, 0], [3, 0, 9, 9.5, 0], [3, 0, 10, 13.15, 0], [3, 0, 11, 0.18, 0], [3, 0, 12, 0.25, 0], [3, 0, 14, 0.15, 0], [3, 0, 15, 0.04, 0], [3, 0, 16, 0.57, 0], [4, 0, 0, 5.95, 0], [4, 0, 2, 1.15, 0], [4, 0, 3, 0.15, 0], [4, 0, 4, 2.89, 0], [4, 0, 5, 1.77, 0], [4, 0, 6, 2.43, 0], [4, 0, 7, 95.61, 0], [4, 0, 8, 0.09, 0], [4, 0, 9, 17.06, 0], [4, 0, 10, 31.76, 0], [4, 0, 11, 0.52, 0], [4, 0, 12, 0.96, 0], [4, 0, 14, 0.85, 0], [4, 0, 15, 0.01, 0], [4, 0, 16, 1.69, 0], [5, 0, 0, 9.95, 0], [5, 0, 1, 0.01, 0], [5, 0, 2, 1.06, 0], [5, 0, 3, 0.39, 0], [5, 0, 4, 2.79, 0], [5, 0, 5, 2.45, 0], [5, 0, 6, 2.26, 0], [5, 0, 7, 85.97, 1], [5, 0, 8, 0.17, 0], [5, 0, 9, 15.23, 0], [5, 0, 10, 27.17, 2], [5, 0, 11, 1.03, 0], [5, 0, 12, 1.38, 0], [5, 0, 14, 1.56, 0], [5, 0, 15, 0.09, 0], [5, 0, 16, 1.13, 0], [6, 0, 0, 1.82, 0], [6, 0, 2, 0.33, 0], [6, 0, 3, 0.02, 0], [6, 0, 4, 1.69, 0], [6, 0, 5, 0.64, 0], [6, 0, 6, 0.41, 0], [6, 0, 7, 63.14, 0], [6, 0, 8, 0.01, 0], [6, 0, 9, 8.73, 0], [6, 0, 10, 11.66, 0], [6, 0, 11, 0.27, 0], [6, 0, 12, 0.14, 0], [6, 0, 13, 0.04, 0], [6, 0, 14, 0.23, 0], [6, 0, 15, 0.05, 0], [6, 0, 16, 0.68, 0], [7, 0, 0, 0.17, 0], [7, 0, 2, 0.05, 0], [7, 0, 4, 3.83, 0], [7, 0, 5, 0.85, 0], [7, 0, 6, 2.02, 0], [7, 0, 7, 50.41, 0], [7, 0, 9, 20.03, 0], [7, 0, 10, 25.76, 0], [7, 0, 11, 1.55, 0], [7, 0, 12, 0.15, 0], [7, 0, 15, 0.03, 0], [7, 0, 16, 0.15, 0], [8, 0, 4, 0.65, 0], [8, 0, 6, 0.06, 0], [8, 0, 7, 15.87, 0], [8, 0, 9, 0.74, 0], [8, 0, 10, 1.36, 5], [8, 0, 11, 0.21, 0], [9, 0, 3, 0.01, 0], [9, 0, 4, 0.23, 0], [9, 0, 6, 0.01, 0], [9, 0, 7, 13.95, 0], [9, 0, 9, 0.26, 0], [9, 0, 10, 0.4, 0], [9, 0, 16, 0.12, 0], [10, 0, 3, 0.01, 0], [10, 0, 4, 2.23, 0], [10, 0, 6, 0.11, 0], [10, 0, 7, 35.4, 1], [10, 0, 9, 8.78, 1], [10, 0, 10, 7.53, 0], [10, 0, 11, 0.45, 0], [10, 0, 16, 0.02, 0], [11, 0, 3, 0.4, 0], [11, 0, 4, 6.07, 0], [11, 0, 5, 0.02, 0], [11, 0, 6, 0.2, 0], [11, 0, 7, 50.3, 4], [11, 0, 8, 0.01, 0], [11, 0, 9, 26.72, 2], [11, 0, 10, 13.26, 3], [11, 0, 11, 0.3, 0], [11, 0, 13, 0.1, 0], [11, 0, 16, 0.08, 0], [12, 0, 0, 0.27, 0], [12, 0, 4, 3.92, 0], [12, 0, 5, 0.02, 0], [12, 0, 6, 0.98, 0], [12, 0, 7, 43.44, 5], [12, 0, 9, 28.28, 7], [12, 0, 10, 13.68, 8], [12, 0, 11, 0.36, 0], [12, 0, 12, 0.02, 0], [12, 0, 13, 1.49, 0], [12, 0, 16, 0.19, 0], [13, 0, 0, 0.06, 0], [13, 0, 2, 0.01, 0], [13, 0, 3, 0.04, 0], [13, 0, 4, 3.93, 0], [13, 0, 6, 0.21, 0], [13, 0, 7, 34.92, 1], [13, 0, 9, 21.15, 0], [13, 0, 10, 10.79, 2], [13, 0, 11, 0.2, 0], [13, 0, 13, 0.41, 0], [13, 0, 16, 0.12, 0], [14, 0, 3, 0.01, 0], [14, 0, 4, 2.67, 0], [14, 0, 6, 0.08, 0], [14, 0, 7, 25.09, 0], [14, 0, 9, 14.5, 0], [14, 0, 10, 6.05, 4], [14, 0, 12, 0.02, 0], [14, 0, 16, 0.06, 0], [15, 0, 0, 0.14, 0], [15, 0, 2, 0.04, 0], [15, 0, 3, 0.11, 0], [15, 0, 4, 8.42, 0], [15, 0, 6, 0.5, 0], [15, 0, 7, 66.52, 1], [15, 0, 8, 0.52, 0], [15, 0, 9, 35.49, 0], [15, 0, 10, 18.74, 0], [15, 0, 11, 0.36, 0], [15, 0, 13, 0.31, 0], [15, 0, 16, 0.22, 0], [16, 0, 0, 0.07, 0], [16, 0, 2, 0.09, 0], [16, 0, 3, 0.08, 0], [16, 0, 4, 7.97, 0], [16, 0, 6, 1.84, 0], [16, 0, 7, 75.21, 3], [16, 0, 8, 0.01, 0], [16, 0, 9, 46.04, 0], [16, 0, 10, 28.52, 2], [16, 0, 11, 0.75, 1], [16, 0, 12, 0.01, 0], [16, 0, 13, 1.28, 0], [16, 0, 16, 0.35, 0], [17, 0, 0, 0.19, 0], [17, 0, 2, 0.12, 0], [17, 0, 3, 0.1, 0], [17, 0, 4, 5.75, 0], [17, 0, 6, 0.96, 0], [17, 0, 7, 65.11, 2], [17, 0, 8, 0.02, 0], [17, 0, 9, 41.77, 1], [17, 0, 10, 19.26, 1], [17, 0, 11, 1.16, 0], [17, 0, 12, 0.08, 0], [17, 0, 13, 1.36, 0], [17, 0, 16, 0.94, 0], [18, 0, 0, 0.14, 0], [18, 0, 2, 0.2, 0], [18, 0, 3, 0.06, 0], [18, 0, 4, 6.17, 0], [18, 0, 5, 0.03, 0], [18, 0, 6, 1.37, 0], [18, 0, 7, 65.01, 4], [18, 0, 8, 0.02, 0], [18, 0, 9, 48.92, 2], [18, 0, 10, 14.53, 0], [18, 0, 11, 0.94, 0], [18, 0, 12, 0.07, 0], [18, 0, 13, 1.41, 0], [18, 0, 16, 0.69, 0], [19, 0, 0, 0.84, 0], [19, 0, 2, 0.3, 0], [19, 0, 3, 0.12, 0], [19, 0, 4, 7.28, 0], [19, 0, 5, 0.04, 0], [19, 0, 6, 0.87, 0], [19, 0, 7, 80.71, 6], [19, 0, 9, 48.97, 1], [19, 0, 10, 15.03, 0], [19, 0, 11, 0.54, 0], [19, 0, 12, 0.1, 0], [19, 0, 13, 2.81, 0], [19, 0, 14, 0.02, 0], [19, 0, 16, 0.74, 0], [20, 0, 0, 0.45, 0], [20, 0, 2, 0.29, 0], [20, 0, 3, 0.74, 0], [20, 0, 4, 4.33, 0], [20, 0, 5, 0.01, 0], [20, 0, 6, 1.08, 0], [20, 0, 7, 103.42, 3], [20, 0, 8, 0.05, 0], [20, 0, 9, 30.53, 0], [20, 0, 10, 14.89, 1], [20, 0, 11, 0.89, 0], [20, 0, 12, 0.05, 0], [20, 0, 13, 1.39, 0], [20, 0, 14, 0.03, 0], [20, 0, 16, 1.36, 0], [21, 0, 0, 0.7, 0], [21, 0, 2, 0.61, 0], [21, 0, 3, 0.19, 0], [21, 0, 4, 17.7, 0], [21, 0, 5, 0.08, 0], [21, 0, 6, 4.53, 0], [21, 0, 7, 261.92, 4], [21, 0, 8, 0.06, 0], [21, 0, 9, 104.8, 2], [21, 0, 10, 82.24, 1], [21, 0, 11, 2.35, 1], [21, 0, 12, 0.21, 0], [21, 0, 13, 2.67, 0], [21, 0, 14, 0.05, 0], [21, 0, 16, 1.89, 0], [22, 0, 0, 2.86, 0], [22, 0, 1, 0.03, 0], [22, 0, 2, 1.55, 0], [22, 0, 3, 0.94, 0], [22, 0, 4, 13.32, 0], [22, 0, 5, 0.44, 0], [22, 0, 6, 4.06, 0], [22, 0, 7, 491.24, 10], [22, 0, 8, 0.21, 0], [22, 0, 9, 127.4, 1], [22, 0, 10, 103.44, 2], [22, 0, 11, 2.65, 0], [22, 0, 12, 0.21, 0], [22, 0, 13, 4.47, 0], [22, 0, 14, 0.17, 0], [22, 0, 15, 0.02, 0], [22, 0, 16, 5.31, 0], [23, 0, 0, 1.58, 0], [23, 0, 2, 2.11, 1], [23, 0, 3, 0.72, 0], [23, 0, 4, 11.52, 0], [23, 0, 5, 0.19, 0], [23, 0, 6, 3.21, 0], [23, 0, 7, 684.68, 8], [23, 0, 8, 0.19, 0], [23, 0, 9, 62.68, 1], [23, 0, 10, 55.84, 0], [23, 0, 11, 3.93, 0], [23, 0, 12, 0.36, 0], [23, 0, 13, 4.85, 0], [23, 0, 14, 0.13, 0], [23, 0, 16, 7.14, 0], [24, 0, 0, 2.09, 0], [24, 0, 2, 1.88, 0], [24, 0, 3, 0.26, 0], [24, 0, 4, 14.29, 0], [24, 0, 5, 0.18, 0], [24, 0, 6, 2.87, 0], [24, 0, 7, 606.17, 7], [24, 0, 8, 0.4, 0], [24, 0, 9, 87.19, 1], [24, 0, 10, 48.65, 0], [24, 0, 11, 3.27, 0], [24, 0, 12, 0.28, 0], [24, 0, 13, 14.44, 0], [24, 0, 14, 0.19, 0], [24, 0, 16, 8.18, 0], [25, 0, 0, 4.86, 0], [25, 0, 2, 1.58, 0], [25, 0, 3, 0.62, 0], [25, 0, 4, 10.3, 0], [25, 0, 5, 0.15, 0], [25, 0, 6, 2.91, 0], [25, 0, 7, 672.34, 12], [25, 0, 8, 0.59, 0], [25, 0, 9, 96.15, 0], [25, 0, 10, 46.37, 6], [25, 0, 11, 3.35, 0], [25, 0, 12, 0.39, 0], [25, 0, 13, 8.46, 0], [25, 0, 14, 0.35, 0], [25, 0, 15, 0.11, 0], [25, 0, 16, 9.47, 0], [26, 0, 0, 0.73, 0], [26, 0, 2, 1.44, 0], [26, 0, 3, 0.84, 0], [26, 0, 4, 11.23, 1], [26, 0, 5, 0.24, 0], [26, 0, 6, 2.32, 0], [26, 0, 7, 695.93, 16], [26, 0, 8, 0.4, 0], [26, 0, 9, 75.43, 2], [26, 0, 10, 44.01, 5], [26, 0, 11, 2.62, 0], [26, 0, 12, 0.38, 0], [26, 0, 13, 9.82, 0], [26, 0, 14, 0.46, 0], [26, 0, 15, 0.1, 0], [26, 0, 16, 9.37, 0], [27, 0, 0, 0.84, 0], [27, 0, 2, 1.02, 0], [27, 0, 3, 0.76, 0], [27, 0, 4, 7.16, 0], [27, 0, 5, 0.16, 0], [27, 0, 6, 4.35, 0], [27, 0, 7, 607.27, 14], [27, 0, 8, 0.37, 0], [27, 0, 9, 79.37, 1], [27, 0, 10, 40.19, 1], [27, 0, 11, 2.8, 0], [27, 0, 12, 0.66, 0], [27, 0, 13, 7.13, 0], [27, 0, 14, 0.46, 0], [27, 0, 15, 0.02, 0], [27, 0, 16, 9.32, 0]], "gdemo": {"gen": [], "age": []}, "campsList": ["BRAND-ACAO-CADASTRO-PRESENCIAL-MESTRADO_DOUTORADO"], "campsModal": ["PRESENCIAL"], "days": ["2026-06-25", "2026-06-26", "2026-06-27", "2026-06-28", "2026-06-29", "2026-06-30", "2026-07-01", "2026-07-02", "2026-07-03", "2026-07-04", "2026-07-05", "2026-07-06", "2026-07-07", "2026-07-08", "2026-07-09", "2026-07-10", "2026-07-11", "2026-07-12", "2026-07-13", "2026-07-14", "2026-07-15", "2026-07-16", "2026-07-17", "2026-07-18", "2026-07-19", "2026-07-20", "2026-07-21", "2026-07-22"], "agList": ["25-34", "35-44", "45-54", "Unknown"], "posList": ["an_classic", "biz_disco_feed", "facebook_notification", "facebook_profile_feed", "facebook_reels", "facebook_reels_overlay", "facebook_stories", "feed", "instagram_explore_grid_home", "instagram_reels", "instagram_stories", "instream_video", "marketplace", "rewarded_video", "right_hand_column", "search", "threads_feed"], "keywords": [], "thumbs": {"BRAND-ACAO-CADASTRO-PRESENCIAL-MESTRADO_DOUTORADO||AD01": "https://external.xx.fbcdn.net/emg1/v/t13/16178800487497713806?url=https%3A%2F%2Fwww.facebook.com%2Fads%2Fimage%2F%3Fd%3DAQKawzjKGXw0j5Ux1TMddrLXoLZp_bdN8IAO2ckVKuK4Y8U7aemTIU_w1vvdBY8t8dh8h75bvVjtG6vsxyV7ykwljGaJLEtoLsY5Bh-oNjYZcNqXENErOUEno5lT6MHFiUvpe_tRckI1tEPvtvFxvPY_&fb_obo=1&utld=facebook.com&stp=c0.5000x0.5000f_dst-emg0_q75_tt6&edm=AOgd6ZUEAAAA&_nc_gid=Hc0R-6oLdp76UYC8BCogfQ&_nc_eui2=AeFmV97sUAlEYj17cLWF3NPHXvjsdPuRRtRe-Ox0-5FG1AWndjV2Sl70pNwrNNcGnRlZ4a0-aPddY806laQn1JVA&_nc_oc=AdpGufH556Ocw2E62xlULkoLe-c1Pq8O9ozPbRPp79Nsc_G7zWAJn2FCbaA2TLbdxh0&ccb=13-1&oh=06_Q3_BAWr9Ea49NwzLQUR1hPd4nsWAsLy3rArJIZa_n40RV_pd&oe=6A63D5B3&_nc_sid=58080a", "BRAND-ACAO-CADASTRO-PRESENCIAL-MESTRADO_DOUTORADO||AD02": "https://scontent.xx.fbcdn.net/v/t15.5256-10/737799971_1532459755198774_4965654254068744501_n.jpg?_nc_cat=100&ccb=1-7&_nc_eui2=AeFR7LBR0jKgWvZt5hh_4599HpBc4OFHfjsekFzg4Ud-O5PLU9mCXMx3xnWOYDYxczz0pT4JgS0XpHaGJG8PDXAX&_nc_ohc=apwrRuXX15UQ7kNvwG80QlQ&_nc_oc=Adpuh_Z8uNuvDhJZpHfngFEOJXyfm2AdotKxvjTw_6zyiAoEsIsENKBUuhqmwKXTAb8&_nc_zt=23&_nc_ht=scontent.xx&edm=AOgd6ZUEAAAA&_nc_gid=Hc0R-6oLdp76UYC8BCogfQ&_nc_tpa=Q5bMBQGnp25Gxt0bnDS7sKC_LT99U9lTtMU_Fl1Dy5FSO1xcYJbuK2itl7SJk5abbVn5oWwmvtRnSt0Z&stp=c0.5000x0.5000f_dst-emg0_q75_tt6&ur=5fad0e&_nc_sid=58080a&oh=00_AQBL8JyPF_Ie9S8Mjp4ve7CMoAcal_93dTbWBJsDfaW-CA&oe=6A67BB08", "BRAND-ACAO-CADASTRO-PRESENCIAL-MESTRADO_DOUTORADO||AD03": "https://scontent.xx.fbcdn.net/v/t15.5256-10/743743984_27278529985183031_5828391560860758363_n.jpg?_nc_cat=101&ccb=1-7&_nc_eui2=AeGl8j0g2updakmYIlxqy7hMC12pc3IkXfsLXalzciRd--tmY7Pqfh8jeT5FuiHDIleKenUuu-t881w-WzZCXQ1x&_nc_ohc=mJCFAbqt0NYQ7kNvwERj2JS&_nc_oc=AdpeRXWsHBb_OdKv2boAZ5tgLov8joZgCBHUNzeuNwk4eQg1OfNCMKkSh-y9P_r4HkY&_nc_zt=23&_nc_ht=scontent.xx&edm=AOgd6ZUEAAAA&_nc_gid=Hc0R-6oLdp76UYC8BCogfQ&_nc_tpa=Q5bMBQE-XaR1WEnDbbuuHFzvkYWHzq98zLxCmBH2vJeEZEPA_j6et40cr8ibUOOI8wPN3fAsX3hVYguU&stp=c0.5000x0.5000f_dst-emg0_q75_tt6&ur=5fad0e&_nc_sid=58080a&oh=00_AQDzEjs3O7dlqfDppqwrdt3wbuBzXJNJqXk_q6L_gBhHBw&oe=6A67A6B0"}, "status": {"BRAND-ACAO-CADASTRO-PRESENCIAL-MESTRADO_DOUTORADO||AD01": "ACTIVE", "BRAND-ACAO-CADASTRO-PRESENCIAL-MESTRADO_DOUTORADO||AD02": "ACTIVE", "BRAND-ACAO-CADASTRO-PRESENCIAL-MESTRADO_DOUTORADO||AD03": "ACTIVE"}, "anos": {"2024": {"meta": [], "google": [], "keywords": []}, "2025": {"meta": [], "google": [], "keywords": []}}}